py_hopscotch_dict/__init__.py
py_hopscotch_dict/hopscotchdict.py
py_hopscotch_dict/py.typed
py_hopscotch_dict/views.py
py_hopscotch_dict-2.1.2.dist-info/LICENSE.md
py_hopscotch_dict-2.1.2.dist-info/METADATA
py_hopscotch_dict-2.1.2.dist-info/WHEEL
py_hopscotch_dict-2.1.2.dist-info/top_level.txt
py_hopscotch_dict-2.1.2.dist-info/RECORD
