Metadata-Version: 2.1
Name: py-hopscotch-dict
Version: 2.1.2
Summary: A replacement for dict using hopscotch hashing.
Author-email: Jeremy Brown <mischif@users.noreply.github.com>
License: # The Prosperity Public License 3.0.0
Project-URL: repository, https://github.com/mischif/py-hopscotch-dict
Classifier: Development Status :: 5 - Production/Stable
Classifier: Intended Audience :: Developers
Classifier: Operating System :: OS Independent
Classifier: Programming Language :: Python :: 3
Classifier: Programming Language :: Python :: 3.9
Classifier: Programming Language :: Python :: 3.10
Classifier: Programming Language :: Python :: 3.11
Classifier: Topic :: Software Development :: Libraries :: Python Modules
Requires-Python: ~=3.9
License-File: LICENSE.md
Provides-Extra: test
Requires-Dist: codecov ; extra == 'test'
Requires-Dist: coverage[toml] ; extra == 'test'
Requires-Dist: hypothesis ; extra == 'test'
Requires-Dist: hypothesis-pytest ; extra == 'test'
Requires-Dist: pytest >=6.0 ; extra == 'test'
Requires-Dist: pytest-cov ; extra == 'test'
